reana_db/__init__.py
reana_db/config.py
reana_db/database.py
reana_db/models.py
reana_db/utils.py
reana_db/version.py
reana_db-0.3.0.dist-info/METADATA
reana_db-0.3.0.dist-info/RECORD
reana_db-0.3.0.dist-info/WHEEL
reana_db-0.3.0.dist-info/top_level.txt
