Metadata-Version: 2.1
Name: reana-db
Version: 0.3.0
Summary: REANA-DB.
Home-page: https://github.com/reanahub/reana-db
Author: REANA
Author-email: info@reana.io
License: UNKNOWN
Platform: UNKNOWN
Classifier: Development Status :: 3 - Alpha
Classifier: Environment :: Web Environment
Classifier: Intended Audience :: Developers
Classifier: License :: OSI Approved :: GNU General Public License v2 (GPLv2)
Classifier: Operating System :: OS Independent
Classifier: Programming Language :: Python :: 3
Classifier: Programming Language :: Python :: 3.6
Classifier: Programming Language :: Python :: Implementation :: CPython
Classifier: Programming Language :: Python
Classifier: Topic :: Internet :: WWW/HTTP :: Dynamic Content
Classifier: Topic :: Software Development :: Libraries :: Python Modules
Provides-Extra: all
Provides-Extra: docs
Provides-Extra: tests
Requires-Dist: psycopg2-binary (>=2.6.1)
Requires-Dist: SQLAlchemy (>=1.2.7)
Requires-Dist: sqlalchemy-utils (>=0.31.0)
Provides-Extra: all
Requires-Dist: Sphinx (>=1.4.4); extra == 'all'
Requires-Dist: sphinx-rtd-theme (>=0.1.9); extra == 'all'
Requires-Dist: check-manifest (>=0.25); extra == 'all'
Requires-Dist: coverage (>=4.0); extra == 'all'
Requires-Dist: httpretty (>=0.8); extra == 'all'
Requires-Dist: isort (>=4.2.2); extra == 'all'
Requires-Dist: pydocstyle (>=1.0.0); extra == 'all'
Requires-Dist: pytest-cache (>=1.0); extra == 'all'
Requires-Dist: pytest-cov (>=1.8.0); extra == 'all'
Requires-Dist: pytest-pep8 (>=1.0.6); extra == 'all'
Requires-Dist: pytest (<3.0.0,>=2.8.0); extra == 'all'
Requires-Dist: Sphinx (>=1.4.4); extra == 'all'
Requires-Dist: sphinx-rtd-theme (>=0.1.9); extra == 'all'
Requires-Dist: check-manifest (>=0.25); extra == 'all'
Requires-Dist: coverage (>=4.0); extra == 'all'
Requires-Dist: httpretty (>=0.8); extra == 'all'
Requires-Dist: isort (>=4.2.2); extra == 'all'
Requires-Dist: pydocstyle (>=1.0.0); extra == 'all'
Requires-Dist: pytest-cache (>=1.0); extra == 'all'
Requires-Dist: pytest-cov (>=1.8.0); extra == 'all'
Requires-Dist: pytest-pep8 (>=1.0.6); extra == 'all'
Requires-Dist: pytest (<3.0.0,>=2.8.0); extra == 'all'
Provides-Extra: docs
Requires-Dist: Sphinx (>=1.4.4); extra == 'docs'
Requires-Dist: sphinx-rtd-theme (>=0.1.9); extra == 'docs'
Provides-Extra: tests
Requires-Dist: check-manifest (>=0.25); extra == 'tests'
Requires-Dist: coverage (>=4.0); extra == 'tests'
Requires-Dist: httpretty (>=0.8); extra == 'tests'
Requires-Dist: isort (>=4.2.2); extra == 'tests'
Requires-Dist: pydocstyle (>=1.0.0); extra == 'tests'
Requires-Dist: pytest-cache (>=1.0); extra == 'tests'
Requires-Dist: pytest-cov (>=1.8.0); extra == 'tests'
Requires-Dist: pytest-pep8 (>=1.0.6); extra == 'tests'
Requires-Dist: pytest (<3.0.0,>=2.8.0); extra == 'tests'
